{
  "db_name": "PostgreSQL",
  "query": "SELECT k.key_bytes, k.encryption_version FROM users u JOIN user_keys k ON u.id = k.user_id WHERE u.did = $1",
  "describe": {
    "columns": [
      {
        "ordinal": 0,
        "name": "key_bytes",
        "type_info": "Bytea"
      },
      {
        "ordinal": 1,
        "name": "encryption_version",
        "type_info": "Int4"
      }
    ],
    "parameters": {
      "Left": [
        "Text"
      ]
    },
    "nullable": [
      false,
      true
    ]
  },
  "hash": "90bcc8fb97f73a0b5f427971aca891936b3f906c2d4cdb4bf203dd6a4c9aa060"
}
