{
  "db_name": "PostgreSQL",
  "query": "SELECT id, migrated_to_pds, handle FROM users WHERE did = $1",
  "describe": {
    "columns": [
      {
        "ordinal": 0,
        "name": "id",
        "type_info": "Uuid"
      },
      {
        "ordinal": 1,
        "name": "migrated_to_pds",
        "type_info": "Text"
      },
      {
        "ordinal": 2,
        "name": "handle",
        "type_info": "Text"
      }
    ],
    "parameters": {
      "Left": [
        "Text"
      ]
    },
    "nullable": [
      false,
      true,
      false
    ]
  },
  "hash": "63cfbd8c2fda2c01cb9a97fc2768b60cafecaa4fa3006c2db9848e852d867073"
}
