{
  "db_name": "PostgreSQL",
  "query": "SELECT code, pending_identifier, expires_at FROM channel_verifications WHERE user_id = $1 AND channel = 'email'",
  "describe": {
    "columns": [
      {
        "ordinal": 0,
        "name": "code",
        "type_info": "Text"
      },
      {
        "ordinal": 1,
        "name": "pending_identifier",
        "type_info": "Text"
      },
      {
        "ordinal": 2,
        "name": "expires_at",
        "type_info": "Timestamptz"
      }
    ],
    "parameters": {
      "Left": [
        "Uuid"
      ]
    },
    "nullable": [
      false,
      true,
      false
    ]
  },
  "hash": "a1464e8d15e8e46a3ebc21e591afb89b8f937469f8e33a43f2cd8e121526f3d3"
}
