{
  "db_name": "PostgreSQL",
  "query": "SELECT two_factor_enabled, preferred_comms_channel as \"preferred_comms_channel: CommsChannel\", id FROM users WHERE did = $1",
  "describe": {
    "columns": [
      {
        "ordinal": 0,
        "name": "two_factor_enabled",
        "type_info": "Bool"
      },
      {
        "ordinal": 1,
        "name": "preferred_comms_channel: CommsChannel",
        "type_info": {
          "Custom": {
            "name": "comms_channel",
            "kind": {
              "Enum": [
                "email",
                "discord",
                "telegram",
                "signal"
              ]
            }
          }
        }
      },
      {
        "ordinal": 2,
        "name": "id",
        "type_info": "Uuid"
      }
    ],
    "parameters": {
      "Left": [
        "Text"
      ]
    },
    "nullable": [
      false,
      false,
      false
    ]
  },
  "hash": "513411270022d2761360a3226e6f46ce6296b5c647e2c7c8c46437c616545b81"
}
